stacy_analyzer/__init__.py
stacy_analyzer/__main__.py
stacy_analyzer/analyzer.py
stacy_analyzer/print_message.py
stacy_analyzer/visitor.py
stacy_analyzer/detectors/AssertBlockHeight.py
stacy_analyzer/detectors/CallInsideAsContract.py
stacy_analyzer/detectors/DivideBeforeMultiply.py
stacy_analyzer/detectors/PrivateFunctionNotUsed.py
stacy_analyzer/detectors/ToDoComment.py
stacy_analyzer/detectors/TxSenderInAssert.py
stacy_analyzer/detectors/UnwrapPanicUsage.py
stacy_analyzer/detectors/UpdatedFunctions.py
stacy_analyzer/detectors/VarCouldBeConstant.py
stacy_analyzer/detectors/__init__.py
stacy_analyzer/tree-sitter-clarity/__init__.py
stacy_analyzer/tree-sitter-clarity/setup.py
stacy_analyzer/tree-sitter-clarity/bindings/__init__.py
stacy_analyzer/tree-sitter-clarity/bindings/python/__init__.py
stacy_analyzer/tree-sitter-clarity/bindings/python/tree_sitter_clarity/__init__.py
stacy_analyzer/tree-sitter-clarity/bindings/python/tree_sitter_clarity/__init__.pyi
stacy_analyzer/tree-sitter-clarity/bindings/python/tree_sitter_clarity/py.typed
stacy_analyzer/tree-sitter-clarity/build/__init__.py
stacy_analyzer-0.1.0.dist-info/LICENSE
stacy_analyzer-0.1.0.dist-info/METADATA
stacy_analyzer-0.1.0.dist-info/WHEEL
stacy_analyzer-0.1.0.dist-info/entry_points.txt
stacy_analyzer-0.1.0.dist-info/top_level.txt
stacy_analyzer-0.1.0.dist-info/RECORD
