Metadata-Version: 2.1
Name: stacy-analyzer
Version: 0.1.0
Summary: Clarity Static Analyzer
Home-page: https://github.com/coinfabrik/stacy
Author: CoinFabrik
Author-email: 
Project-URL: Documentation, https://github.com/coinfabrik/stacy
Project-URL: Bug Reports, https://github.com/coinfabrik/stacy/issues
Project-URL: Source Code, https://github.com/coinfabrik/stacy
Keywords: stacks,auditor,security,clarity,smart-contracts
Classifier: Intended Audience :: Developers
Classifier: Development Status :: 3 - Alpha
Classifier: Environment :: Console
Classifier: License :: OSI Approved :: MIT License
Classifier: Natural Language :: English
Classifier: Topic :: Software Development
Classifier: Topic :: Utilities
Requires-Python: >=3.6
License-File: LICENSE
Requires-Dist: tree-sitter
Requires-Dist: tree-sitter-clarity
